[
	{
		"reservationStatus": "reservation_finish",
		"submitTime": "2022-12-30 22:46:11",
		"date": "2023-01-02",
		"startTime": "10:00",
		"endTime": "11:00",
		"FK_FdTableBean_Id": 11,
		"actualEndTime": "2023-01-02 10:20:52",
		"pNumber": 2,
		"name": "葉婉妃",
		"gender": "M",
		"phone": "0904421252",
		"email": null,
		"note": null,
		"id": 1
	},
	{
		"reservationStatus": "reservation_finish",
		"submitTime": "2022-12-31 02:08:10",
		"date": "2023-01-04",
		"startTime": "17:00",
		"endTime": "18:00",
		"FK_FdTableBean_Id": 3,
		"actualEndTime": "2023-01-04 17:28:24",
		"pNumber": 1,
		"name": "劉彥紫",
		"gender": "M",
		"phone": "0943568569",
		"email": null,
		"note": null,
		"id": 2
	},
	{
		"reservationStatus": "reservation_finish",
		"submitTime": "2022-12-31 02:27:15",
		"date": "2023-01-02",
		"startTime": "18:00",
		"endTime": "19:00",
		"FK_FdTableBean_Id": 19,
		"actualEndTime": "2023-01-02 18:20:34",
		"pNumber": 3,
		"name": "江惠美",
		"gender": "M",
		"phone": "0926675638",
		"email": null,
		"note": null,
		"id": 3
	},
	{
		"reservationStatus": "reservation_finish",
		"submitTime": "2022-12-31 19:07:28",
		"date": "2023-01-06",
		"startTime": "10:00",
		"endTime": "11:00",
		"FK_FdTableBean_Id": 9,
		"actualEndTime": "2023-01-06 10:31:41",
		"pNumber": 4,
		"name": "陳士銘",
		"gender": "F",
		"phone": "0914165977",
		"email": null,
		"note": null,
		"id": 4
	},
	{
		"reservationStatus": "reservation_finish",
		"submitTime": "2023-01-01 01:24:06",
		"date": "2023-01-07",
		"startTime": "09:00",
		"endTime": "10:00",
		"FK_FdTableBean_Id": 8,
		"actualEndTime": "2023-01-07 09:46:51",
		"pNumber": 4,
		"name": "陳士銘",
		"gender": "F",
		"phone": "0914165977",
		"email": null,
		"note": null,
		"id": 5
	},
	{
		"reservationStatus": "reservation_finish",
		"submitTime": "2023-01-02 11:13:21",
		"date": "2023-01-05",
		"startTime": "16:00",
		"endTime": "17:00",
		"FK_FdTableBean_Id": 10,
		"actualEndTime": "2023-01-05 16:34:33",
		"pNumber": 3,
		"name": "陳慈豪",
		"gender": "M",
		"phone": "0915950215",
		"email": null,
		"note": null,
		"id": 6
	},
	{
		"reservationStatus": "reservation_finish",
		"submitTime": "2023-01-03 11:04:55",
		"date": "2023-01-04",
		"startTime": "11:00",
		"endTime": "12:00",
		"FK_FdTableBean_Id": 17,
		"actualEndTime": "2023-01-04 11:33:30",
		"pNumber": 2,
		"name": "顏江琳",
		"gender": "F",
		"phone": "0943082820",
		"email": null,
		"note": null,
		"id": 7
	},
	{
		"reservationStatus": "reservation_finish",
		"submitTime": "2023-01-04 03:57:05",
		"date": "2023-01-09",
		"startTime": "15:00",
		"endTime": "16:00",
		"FK_FdTableBean_Id": 16,
		"actualEndTime": "2023-01-09 15:28:13",
		"pNumber": 1,
		"name": "黎至筠",
		"gender": "M",
		"phone": "0961922610",
		"email": null,
		"note": null,
		"id": 8
	},
	{
		"reservationStatus": "reservation_finish",
		"submitTime": "2023-01-07 17:20:27",
		"date": "2023-01-09",
		"startTime": "16:00",
		"endTime": "17:00",
		"FK_FdTableBean_Id": 20,
		"actualEndTime": "2023-01-09 16:36:10",
		"pNumber": 3,
		"name": "李怡潔",
		"gender": "F",
		"phone": "0944171159",
		"email": null,
		"note": null,
		"id": 9
	}
]